pyadt/__init__.py
pyadt/__version__.py
pyadt/api.py
pyadt/exceptions.py
pyadt-1.0.0.dist-info/LICENSE
pyadt-1.0.0.dist-info/METADATA
pyadt-1.0.0.dist-info/WHEEL
pyadt-1.0.0.dist-info/top_level.txt
pyadt-1.0.0.dist-info/RECORD
