Metadata-Version: 2.1
Name: pyadt
Version: 1.0.0
Summary: A wrapper for working with ADT tables in Python 3.7
Home-page: https://github.com/alexmacniven/pyadt
Author: Alex Macniven
Author-email: apmacniven@outlook.com
License: ISC
Requires-Dist: pyodbc
